eryx/__init__.py
eryx/__main__.py
eryx/frontend/__init__.py
eryx/frontend/ast.py
eryx/frontend/lexer.py
eryx/frontend/parser.py
eryx/frontend/syntax_highlighter.py
eryx/frontend/transpiler.py
eryx/packages/__init__.py
eryx/packages/packages.py
eryx/runtime/__init__.py
eryx/runtime/environment.py
eryx/runtime/interpreter.py
eryx/runtime/repl.py
eryx/runtime/runner.py
eryx/runtime/values.py
eryx/server/__init__.py
eryx/server/ide.py
eryx/server/static/eryx.ico
eryx/server/static/main.js
eryx/server/static/style.css
eryx/server/templates/index.html
eryx/tests/__init__.py
eryx/tests/make_tests.py
eryx/tests/run_test.py
eryx/tests/test/builtins/builtins.eryx
eryx/tests/test/builtins/builtins.eryx.ast
eryx/tests/test/builtins/builtins.eryx.output
eryx/tests/test/builtins/test.info
eryx/tests/test/classes/classes.eryx
eryx/tests/test/classes/classes.eryx.ast
eryx/tests/test/classes/classes.eryx.output
eryx/tests/test/classes/test.info
eryx/tests/test/comments/comments.eryx
eryx/tests/test/comments/comments.eryx.ast
eryx/tests/test/comments/comments.eryx.output
eryx/tests/test/comments/test.info
eryx/tests/test/concat/concat.eryx
eryx/tests/test/concat/concat.eryx.ast
eryx/tests/test/concat/concat.eryx.output
eryx/tests/test/concat/test.info
eryx/tests/test/enums/enums.eryx
eryx/tests/test/enums/enums.eryx.ast
eryx/tests/test/enums/enums.eryx.output
eryx/tests/test/enums/test.info
eryx/tests/test/for_loops/for_loops.eryx
eryx/tests/test/for_loops/for_loops.eryx.ast
eryx/tests/test/for_loops/for_loops.eryx.output
eryx/tests/test/for_loops/test.info
eryx/tests/test/functions/functions.eryx
eryx/tests/test/functions/functions.eryx.ast
eryx/tests/test/functions/functions.eryx.output
eryx/tests/test/functions/test.info
eryx/tests/test/if_else_statements/if_else_statements.eryx
eryx/tests/test/if_else_statements/if_else_statements.eryx.ast
eryx/tests/test/if_else_statements/if_else_statements.eryx.output
eryx/tests/test/if_else_statements/test.info
eryx-0.5.7.dist-info/licenses/LICENSE
eryx-0.5.7.dist-info/METADATA
eryx-0.5.7.dist-info/WHEEL
eryx-0.5.7.dist-info/entry_points.txt
eryx-0.5.7.dist-info/top_level.txt
eryx-0.5.7.dist-info/RECORD
