Metadata-Version: 2.4
Name: Eryx
Version: 0.5.7
Summary: A decently fast and simple dynamically typed programming language similar to javascript/python.
Author: ShyMike
License: MIT
Project-URL: Documentation, https://imshymike.github.io/Eryx
Project-URL: Source, https://github.com/ImShyMike/Eryx
Classifier: Programming Language :: Python :: 3
Classifier: License :: OSI Approved :: MIT License
Classifier: Operating System :: OS Independent
Requires-Python: >=3.10
License-File: LICENSE
Requires-Dist: colorama
Requires-Dist: flask
Requires-Dist: pytest
Requires-Dist: toml
Requires-Dist: requests
Dynamic: license-file
